pysmartweatherio/__init__.py
pysmartweatherio/api.py
pysmartweatherio/models.py
pysmartweatherio/utils.py
pysmartweatherio-0.2.8.dist-info/LICENSE
pysmartweatherio-0.2.8.dist-info/METADATA
pysmartweatherio-0.2.8.dist-info/WHEEL
pysmartweatherio-0.2.8.dist-info/top_level.txt
pysmartweatherio-0.2.8.dist-info/RECORD
